harmonique.py
harmonique-0.0.3.dist-info/METADATA
harmonique-0.0.3.dist-info/WHEEL
harmonique-0.0.3.dist-info/entry_points.txt
harmonique-0.0.3.dist-info/top_level.txt
harmonique-0.0.3.dist-info/RECORD
